{
  "title": "Examen del Capítulo 9: Clima y Estaciones",
  "questions": [
    {
      "id": 2,
      "type": "multipleChoice",
      "question": "¿Cómo se dice \"soleado\" en inglés?",
      "explanation": "\"Sunny\" significa \"soleado\" en inglés.",
      "correctAnswer": "Sunny",
      "options": [
        "Rainy",
        "Cloudy",
        "Sunny",
        "Snowy"
      ]
    },
    {
      "id": 4,
      "type": "fillInTheBlank",
      "question": "Completa el clima: \"___\" (lluvioso)",
      "explanation": "\"Rainy\" significa \"lluvioso\" en inglés.",
      "correctAnswer": "Rainy",
      "options": [
        "Sunny",
        "Rainy",
        "Cloudy",
        "Snowy"
      ]
    },
    {
      "id": 6,
      "type": "multipleChoice",
      "question": "¿Cómo se dice \"nublado\" en inglés?",
      "explanation": "\"Cloudy\" significa \"nublado\" en inglés.",
      "correctAnswer": "Cloudy",
      "options": [
        "Sunny",
        "Rainy",
        "Cloudy",
        "Snowy"
      ]
    },
    {
      "id": 8,
      "type": "fillInTheBlank",
      "question": "Completa el clima: \"___\" (nevado)",
      "explanation": "\"Snowy\" significa \"nevado\" en inglés.",
      "correctAnswer": "Snowy",
      "options": [
        "Sunny",
        "Rainy",
        "Cloudy",
        "Snowy"
      ]
    },
    {
      "id": 10,
      "type": "multipleChoice",
      "question": "¿Cómo se dice \"primavera\" en inglés?",
      "explanation": "\"Spring\" significa \"primavera\" en inglés.",
      "correctAnswer": "Spring",
      "options": [
        "Summer",
        "Spring",
        "Fall",
        "Winter"
      ]
    },
    {
      "id": 12,
      "type": "fillInTheBlank",
      "question": "Completa la estación: \"___\" (verano)",
      "explanation": "\"Summer\" significa \"verano\" en inglés.",
      "correctAnswer": "Summer",
      "options": [
        "Spring",
        "Summer",
        "Fall",
        "Winter"
      ]
    },
    {
      "id": 14,
      "type": "multipleChoice",
      "question": "¿Cómo se dice \"otoño\" en inglés?",
      "explanation": "\"Fall\" significa \"otoño\" en inglés.",
      "correctAnswer": "Fall",
      "options": [
        "Spring",
        "Summer",
        "Fall",
        "Winter"
      ]
    },
    {
      "id": 16,
      "type": "fillInTheBlank",
      "question": "Completa la estación: \"___\" (invierno)",
      "explanation": "\"Winter\" significa \"invierno\" en inglés.",
      "correctAnswer": "Winter",
      "options": [
        "Spring",
        "Summer",
        "Fall",
        "Winter"
      ]
    },
    {
      "id": 18,
      "type": "multipleChoice",
      "question": "¿Cómo se pregunta \"¿Qué tiempo hace?\" en inglés?",
      "explanation": "\"What's the weather like?\" es la forma correcta de preguntar.",
      "correctAnswer": "What's the weather like?",
      "options": [
        "What's the weather like?",
        "How's the weather?",
        "What weather is it?",
        "How weather is it?"
      ]
    },
    {
      "id": 20,
      "type": "fillInTheBlank",
      "question": "Completa la respuesta: \"It's ___\" (Está soleado)",
      "explanation": "\"It's sunny\" significa \"Está soleado\".",
      "correctAnswer": "sunny",
      "options": [
        "sunny",
        "rainy",
        "cloudy",
        "snowy"
      ]
    },
    {
      "id": 22,
      "type": "multipleChoice",
      "question": "¿Cómo se dice \"caliente\" en inglés?",
      "explanation": "\"Hot\" significa \"caliente\" en inglés.",
      "correctAnswer": "Hot",
      "options": [
        "Cold",
        "Hot",
        "Warm",
        "Cool"
      ]
    },
    {
      "id": 24,
      "type": "fillInTheBlank",
      "question": "Completa la temperatura: \"___\" (frío)",
      "explanation": "\"Cold\" significa \"frío\" en inglés.",
      "correctAnswer": "Cold",
      "options": [
        "Hot",
        "Cold",
        "Warm",
        "Cool"
      ]
    },
    {
      "id": 26,
      "type": "multipleChoice",
      "question": "¿Cómo se dice \"cálido\" en inglés?",
      "explanation": "\"Warm\" significa \"cálido\" en inglés.",
      "correctAnswer": "Warm",
      "options": [
        "Hot",
        "Cold",
        "Warm",
        "Cool"
      ]
    },
    {
      "id": 28,
      "type": "fillInTheBlank",
      "question": "Completa la temperatura: \"___\" (fresco)",
      "explanation": "\"Cool\" significa \"fresco\" en inglés.",
      "correctAnswer": "Cool",
      "options": [
        "Hot",
        "Cold",
        "Warm",
        "Cool"
      ]
    },
    {
      "id": 30,
      "type": "multipleChoice",
      "question": "¿Cómo se dice \"actividades relacionadas con el clima\" en inglés?",
      "explanation": "\"Weather-related activities\" significa \"actividades relacionadas con el clima\".",
      "correctAnswer": "Weather-related activities",
      "options": [
        "Weather activities",
        "Climate activities",
        "Weather-related activities",
        "Climate-related activities"
      ]
    },
    {
      "id": 32,
      "type": "fillInTheBlank",
      "question": "Completa la frase: \"I like ___ weather\" (Me gusta el clima cálido)",
      "explanation": "\"I like warm weather\" significa \"Me gusta el clima cálido\".",
      "correctAnswer": "warm",
      "options": [
        "hot",
        "cold",
        "warm",
        "cool"
      ]
    }
  ],
  "totalQuestions": 16,
  "createdAt": "2025-08-03T23:25:24.037Z"
}